{
  "id": "milkdrop:martin-ludicrous-speed",
  "schema_version": 2,
  "source": {
    "type": "milkdrop",
    "loader": "url",
    "url": "/presets/milkdrop/martin-ludicrous-speed.milk",
    "format": "milk-v201"
  },
  "display": {
    "name": "martin - ludicrous speed",
    "author": "martin"
  },
  "annotation": null,
  "assets": {
    "textures_needed": [],
    "video": "/videos/milkdrop_martin-ludicrous-speed.webm",
    "thumb": "/thumbs/milkdrop_martin-ludicrous-speed.jpg"
  },
  "contribution": {
    "added_by": "scottspace",
    "added_at": "2026-05-30T17:43:37.530Z",
    "license": "MIT"
  },
  "compatibility": {
    "renders": false,
    "note": "capture was empty (24814 bytes); preset doesn't render meaningfully against the current test signal"
  }
}
